gooder_ai/__init__.py
gooder_ai/auth/__init__.py
gooder_ai/auth/types.py
gooder_ai/configs/__init__.py
gooder_ai/configs/gooder-configs/user-config.json
gooder_ai/globals.py
gooder_ai/s3/__init__.py
gooder_ai/s3/types.py
gooder_ai/types.py
gooder_ai/utils.py
gooder_ai/view/__init__.py
gooder_ai/view/types.py
gooder_ai/wrapper.py
gooder_ai-1.4.1.dist-info/entry_points.txt
gooder_ai-1.4.1.dist-info/METADATA
gooder_ai-1.4.1.dist-info/WHEEL
gooder_ai-1.4.1.dist-info/RECORD
