Metadata-Version: 2.3
Name: gooder-ai
Version: 1.4.1
Summary: 
Keywords: MLvaluation,modelvaluation,ML valuation,model valuation
Author: Eric Siegel
Author-email: eric@predictionimpact.com
Requires-Python: >=3.11,<4.0
Classifier: Programming Language :: Python :: 3
Classifier: Programming Language :: Python :: 3.11
Classifier: Programming Language :: Python :: 3.12
Classifier: Programming Language :: Python :: 3.13
Requires-Dist: aiohttp (>=3.11.11,<4.0.0)
Requires-Dist: boto3 (>=1.36.7,<2.0.0)
Requires-Dist: numpy (>=2.2.3,<3.0.0)
Requires-Dist: pandas (>=2.2.3,<3.0.0)
Requires-Dist: scipy (>=1.15.2,<2.0.0)
